realitydb/__init__.py
realitydb/_proxy.py
realitydb/documents.py
realitydb/models.py
realitydb/py.typed
realitydb/rpc_server.py
realitydb/utils.py
realitydb/vectorstore.py
realitydb-0.0.2.dist-info/METADATA
realitydb-0.0.2.dist-info/WHEEL
realitydb-0.0.2.dist-info/entry_points.txt
realitydb-0.0.2.dist-info/RECORD
